CyPkgDemo-0.0.1rc6.dist-info/METADATA
CyPkgDemo-0.0.1rc6.dist-info/RECORD
CyPkgDemo-0.0.1rc6.dist-info/WHEEL
CyPkgDemo-0.0.1rc6.dist-info/top_level.txt
cypkgdemo/__init__.py
cypkgdemo/atoi.pxd
cypkgdemo/atoi.so
cypkgdemo/calc.so
cypkgdemo/calc_py.py
cypkgdemo/sin.pxd
