Metadata-Version: 2.1
Name: CyPkgDemo
Version: 0.0.1rc6
Summary: A demo of organizing, building and distributing a Python-Cython mixed package.
Home-page: UNKNOWN
Author: psrit
Author-email: xiaojx13@outlook.com
License: UNKNOWN
Platform: UNKNOWN
Provides-Extra: cython
Provides-Extra: cython
Requires-Dist: cython; extra == 'cython'
